{"cameraMode":{"drawMode":0,"name":"Shaded","section":"Shading Mode"},"sceneLighting":true,"audioPlay":false,"sceneViewState":{"m_AlwaysRefresh":false,"showFog":true,"showSkybox":true,"showFlares":true,"showImageEffects":true,"showParticleSystems":true,"showVisualEffectGraphs":true,"m_FxEnabled":true},"in2DMode":false,"pivot":{"x":106.0,"y":71.0,"z":0.0},"rotation":{"x":0.04093281179666519,"y":-0.9581353664398193,"z":0.22080637514591218,"w":0.17761635780334474},"size":81.39410400390625,"orthographic":false}